youcomsum/__init__.py
youcomsum/__main__.py
youcomsum/cli.py
youcomsum/core.py
youcomsum/info.py
youcomsum/prompts/batch_prompt.txt
youcomsum/prompts/rating_prompt.txt
youcomsum/prompts/rating_template.txt
youcomsum/prompts/summarize_prompt.txt
youcomsum/py.typed
youcomsum-0.0.1.dist-info/LICENSE
youcomsum-0.0.1.dist-info/METADATA
youcomsum-0.0.1.dist-info/WHEEL
youcomsum-0.0.1.dist-info/entry_points.txt
youcomsum-0.0.1.dist-info/RECORD
