Metadata-Version: 2.1
Name: youcomsum
Version: 0.0.1
Summary: Batch summarize YouTube video comments using artificial intelligence (OpenAI, ...).
Home-page: https://github.com/Dashstrom/youcomsum
License: MIT
Keywords: python
Author: Dashstrom
Author-email: dashstrom.pro@gmail.com
Maintainer: Dashstrom
Maintainer-email: dashstrom.pro@gmail.com
Requires-Python: >=3.9,<3.14
Classifier: Development Status :: 3 - Alpha
Classifier: Environment :: Console
Classifier: Framework :: Pytest
Classifier: Framework :: Sphinx
Classifier: Framework :: tox
Classifier: Intended Audience :: Developers
Classifier: Intended Audience :: System Administrators
Classifier: License :: OSI Approved :: MIT License
Classifier: Natural Language :: English
Classifier: Operating System :: OS Independent
Classifier: Programming Language :: Python :: 3
Classifier: Programming Language :: Python :: 3.9
Classifier: Programming Language :: Python :: 3.10
Classifier: Programming Language :: Python :: 3.11
Classifier: Programming Language :: Python :: 3.12
Classifier: Programming Language :: Python :: 3.13
Classifier: Programming Language :: Python :: 3 :: Only
Classifier: Typing :: Typed
Provides-Extra: cov
Provides-Extra: docs
Provides-Extra: format
Provides-Extra: lint
Provides-Extra: tasks
Provides-Extra: test
Requires-Dist: commitizen (==4.1.1) ; extra == "tasks"
Requires-Dist: coverage[toml] (==7.6.10) ; extra == "cov"
Requires-Dist: mypy (==1.14.1) ; extra == "lint" or extra == "format"
Requires-Dist: openai
Requires-Dist: poethepoet (==0.32.2) ; extra == "tasks"
Requires-Dist: pre-commit (==4.1.0) ; extra == "tasks"
Requires-Dist: pre-commit-hooks (==5.0.0) ; extra == "tasks"
Requires-Dist: pycountry (>=24.6.1,<25.0.0)
Requires-Dist: pytest (==8.3.4) ; extra == "test" or extra == "cov" or extra == "lint" or extra == "format"
Requires-Dist: pytest-cov (==6.0.0) ; extra == "cov"
Requires-Dist: pytest-mock (==3.14.0) ; extra == "test" or extra == "cov" or extra == "lint" or extra == "format"
Requires-Dist: ruff (==0.9.4) ; extra == "lint" or extra == "format"
Requires-Dist: sphinx (==7.4.7) ; extra == "docs"
Requires-Dist: sphinx-rtd-theme (==3.0.2) ; extra == "docs"
Requires-Dist: sphinxcontrib-mermaid (==1.0.0) ; extra == "docs"
Requires-Dist: torch (>=2.6.0,<3.0.0)
Requires-Dist: transformers (>=4.50.0,<5.0.0)
Requires-Dist: types-tqdm (==4.67.0.20241221) ; extra == "lint" or extra == "format"
Requires-Dist: typing-extensions (>=4.8.0)
Requires-Dist: youtube-comment-downloader
Project-URL: Documentation, https://dashstrom.github.io/youcomsum
Project-URL: Repository, https://github.com/Dashstrom/youcomsum
